mathcraft/__init__.py
mathcraft/contexts.py
mathcraft/curve_fitting.py
mathcraft/linalg.py
mathcraft/ode.py
math_craft-0.1.0.dist-info/LICENSE
math_craft-0.1.0.dist-info/METADATA
math_craft-0.1.0.dist-info/WHEEL
math_craft-0.1.0.dist-info/entry_points.txt
math_craft-0.1.0.dist-info/top_level.txt
math_craft-0.1.0.dist-info/RECORD
