Metadata-Version: 2.1
Name: math-craft
Version: 0.1.0
Summary: A MatLab like Python package for academics, students, and enthusiasts
Home-page: https://github.com/mbenencase/mathcraft
Author: Marcelo Eduardo Benencase
Author-email: marcelo.benencase@gmail.com
License: UNKNOWN
Platform: UNKNOWN
Classifier: Programming Language :: Python :: 3
Classifier: License :: OSI Approved :: MIT License
Classifier: Operating System :: OS Independent
License-File: LICENSE
Requires-Dist: beartype
Requires-Dist: matplotlib
Requires-Dist: numpy
Requires-Dist: scipy
